global_contrast_factor/__init__.py
global_contrast_factor/global_contrast_factor.py
global_contrast_factor_python-0.0.1.dist-info/METADATA
global_contrast_factor_python-0.0.1.dist-info/WHEEL
global_contrast_factor_python-0.0.1.dist-info/top_level.txt
global_contrast_factor_python-0.0.1.dist-info/RECORD
