Metadata-Version: 2.1
Name: global-contrast-factor-python
Version: 0.0.1
Summary: Global contrast Factor  - Python
Home-page: https://github.com/jinwonkim93/global-contrast-factor-python
Author: Jinwon Kim
Author-email: code.eric22@gmail.com
License: MIT
Keywords: contrast,image
Platform: UNKNOWN
Requires-Dist: opencv-python
Requires-Dist: numpy
